{
  "total": 7,
  "tools inspection": {
    "Code Inspection": 7
  },
  "attributes": {
    "vcs": {
      "sarifIdea": {
        "repositoryUri": "https://github.com/smockoro/ts-sample",
        "revisionId": "0d883940898609b7fd02b226d5967353727d704c",
        "branch": "renovate/fastify-docker"
      }
    },
    "deviceId": "200820300000000-a2e4-ac03-11f5-d5edf282343f",
    "jobUrl": "https://github.com/smockoro/ts-sample/actions/runs/3414273852",
    "repoUrl": "https://github.com/smockoro/ts-sample"
  }
}