{"version":"3","listProblem":[{
  "tool": "Code Inspection",
  "category": "Async code and promises",
  "type": "Result of method call returning a promise is ignored",
  "severity": "Moderate",
  "comment": "Promise returned from start is ignored",
  "detailsInfo": "Reports a function call that returns a `Promise` that is not used later. Such calls are usually unintended and indicate an error.",
  "sources": [
    {
      "type": "file",
      "path": "fastify-docker/src/server.ts",
      "language": "JavaScript",
      "line": 17,
      "offset": 1,
      "length": 5,
      "code": {
        "startLine": 15,
        "length": 5,
        "offset": 5,
        "surroundingCode": "}\r\n\r\nstart()\r\n"
      }
    }
  ],
  "attributes": {
    "module": "project",
    "inspectionName": "JSIgnoredPromiseFromCall"
  },
  "hash": "a9438cccedd2d3625842ed22a5711d59f5c529938df64516c52e47d3cdefe560"
},{
  "tool": "Code Inspection",
  "category": "Unused symbols",
  "type": "Unused local symbol",
  "severity": "High",
  "comment": "Unused parameter request",
  "detailsInfo": "Reports an unused locally accessible parameter, local variable, function, class, or private member declaration.",
  "sources": [
    {
      "type": "file",
      "path": "fastify-docker/src/adapter/http/route/ping.ts",
      "language": "JavaScript",
      "line": 20,
      "offset": 38,
      "length": 7,
      "code": {
        "startLine": 18,
        "length": 7,
        "offset": 42,
        "surroundingCode": "}\r\n\r\nexport const pingController = async (request: FastifyRequest, reply: FastifyReply) => {\r\n  //throw new SystemError('E111')\r\n  return { pong: \"it worked!!\" }\r"
      }
    }
  ],
  "attributes": {
    "module": "project",
    "inspectionName": "JSUnusedLocalSymbols"
  },
  "hash": "75e5c9aaa92bde4c34f1bbadc57e1f389a7be251aeb28488e69cc8c8c33a03f4"
},{
  "tool": "Code Inspection",
  "category": "Unused symbols",
  "type": "Unused local symbol",
  "severity": "High",
  "comment": "Unused parameter reply",
  "detailsInfo": "Reports an unused locally accessible parameter, local variable, function, class, or private member declaration.",
  "sources": [
    {
      "type": "file",
      "path": "fastify-docker/src/adapter/http/route/ping.ts",
      "language": "JavaScript",
      "line": 20,
      "offset": 63,
      "length": 5,
      "code": {
        "startLine": 18,
        "length": 5,
        "offset": 67,
        "surroundingCode": "}\r\n\r\nexport const pingController = async (request: FastifyRequest, reply: FastifyReply) => {\r\n  //throw new SystemError('E111')\r\n  return { pong: \"it worked!!\" }\r"
      }
    }
  ],
  "attributes": {
    "module": "project",
    "inspectionName": "JSUnusedLocalSymbols"
  },
  "hash": "de1732ade8745c8238e7df3d5c8442ae789bbcafb56a41b777b7291f397f5ab5"
},{
  "tool": "Code Inspection",
  "category": "General",
  "type": "Unresolved JavaScript variable",
  "severity": "Moderate",
  "comment": "Unresolved variable or type module",
  "detailsInfo": "Reports an unresolved referenced variable or field.\n\nTypeScript code is ignored.",
  "sources": [
    {
      "type": "file",
      "path": "fastify-docker/jest.config.js",
      "language": "JavaScript",
      "line": 2,
      "offset": 1,
      "length": 6,
      "code": {
        "startLine": 1,
        "length": 6,
        "offset": 66,
        "surroundingCode": "/** @type {import('ts-jest/dist/types').InitialOptionsTsJest} */\r\nmodule.exports = {\r\n    preset: 'ts-jest',\r\n    testEnvironment: 'node',\r"
      }
    }
  ],
  "attributes": {
    "module": "project",
    "inspectionName": "JSUnresolvedVariable"
  },
  "hash": "8d1dcdaf0df91a9c60821a64e9793089d5649566b0d45dcd71cfc7561ca24fc9"
},{
  "tool": "Code Inspection",
  "category": "General",
  "type": "Unresolved JavaScript variable",
  "severity": "Moderate",
  "comment": "Unresolved variable or type module",
  "detailsInfo": "Reports an unresolved referenced variable or field.\n\nTypeScript code is ignored.",
  "sources": [
    {
      "type": "file",
      "path": "express-docker/jest.config.js",
      "language": "JavaScript",
      "line": 2,
      "offset": 1,
      "length": 6,
      "code": {
        "startLine": 1,
        "length": 6,
        "offset": 66,
        "surroundingCode": "/** @type {import('ts-jest/dist/types').InitialOptionsTsJest} */\r\nmodule.exports = {\r\n    preset: 'ts-jest',\r\n    testEnvironment: 'node',\r"
      }
    }
  ],
  "attributes": {
    "module": "project",
    "inspectionName": "JSUnresolvedVariable"
  },
  "hash": "2879e739e19d46c67870e821f0646d3fcc4c2a41f950f8181c9f75b6fa1ebdb5"
},{
  "tool": "Code Inspection",
  "category": "General",
  "type": "Unresolved JavaScript variable",
  "severity": "Moderate",
  "comment": "Unresolved variable or type module",
  "detailsInfo": "Reports an unresolved referenced variable or field.\n\nTypeScript code is ignored.",
  "sources": [
    {
      "type": "file",
      "path": "fastify-docker/.prettierrc.js",
      "language": "JavaScript",
      "line": 2,
      "offset": 1,
      "length": 6,
      "code": {
        "startLine": 1,
        "length": 6,
        "offset": 45,
        "surroundingCode": "// https://prettier.io/docs/en/options.html\r\nmodule.exports = {\r\n    tabWidth: 2, //インデントのスペース数\r\n    singleQuote: true, //シングルクォートに統一\r"
      }
    }
  ],
  "attributes": {
    "module": "project",
    "inspectionName": "JSUnresolvedVariable"
  },
  "hash": "e558f9801302bffc8c6a8188868d7adcaa0403a912e7e18aa118ebe9d2308fe7"
},{
  "tool": "Code Inspection",
  "category": "General",
  "type": "Unresolved JavaScript variable",
  "severity": "Moderate",
  "comment": "Unresolved variable or type module",
  "detailsInfo": "Reports an unresolved referenced variable or field.\n\nTypeScript code is ignored.",
  "sources": [
    {
      "type": "file",
      "path": "express-docker/.prettierrc.js",
      "language": "JavaScript",
      "line": 2,
      "offset": 1,
      "length": 6,
      "code": {
        "startLine": 1,
        "length": 6,
        "offset": 45,
        "surroundingCode": "// https://prettier.io/docs/en/options.html\r\nmodule.exports = {\r\n    tabWidth: 2, //インデントのスペース数\r\n    singleQuote: true, //シングルクォートに統一\r"
      }
    }
  ],
  "attributes": {
    "module": "project",
    "inspectionName": "JSUnresolvedVariable"
  },
  "hash": "3c2b2c069b71f9ac89f0c91755b8c4158f03d66897f47daca601da2f92b7bb16"
}]}